todo/__init__.py
todo/__main__.py
todo/file_utils.py
todo/interactive_shell.py
todo/task_manager.py
todo_list_cli-1.1.2.dist-info/LICENSE
todo_list_cli-1.1.2.dist-info/METADATA
todo_list_cli-1.1.2.dist-info/WHEEL
todo_list_cli-1.1.2.dist-info/entry_points.txt
todo_list_cli-1.1.2.dist-info/top_level.txt
todo_list_cli-1.1.2.dist-info/RECORD
