Metadata-Version: 2.1
Name: todo-list-cli
Version: 1.1.2
Summary: A CLI todo app built with Typer and Rich
Home-page: https://github.com/renancavalcantercb/todo-list-cli
Author: Renan Cavalcante
Author-email: renancavalcantercb@protonmail.com
License: MIT
Classifier: Programming Language :: Python :: 3
Classifier: License :: OSI Approved :: MIT License
Classifier: Operating System :: OS Independent
Requires-Python: >=3.7
License-File: LICENSE
Requires-Dist: rich
Requires-Dist: typer[all]
